README.md
setup.py
proto3parser/__init__.py
proto3parser/parser.py
proto3parser.egg-info/PKG-INFO
proto3parser.egg-info/SOURCES.txt
proto3parser.egg-info/dependency_links.txt
proto3parser.egg-info/requires.txt
proto3parser.egg-info/top_level.txt
test/test.py