Metadata-Version: 2.1
Name: proto3parser
Version: 0.0.1
Summary: A package for parsing proto3 files
Home-page: https://github.com/khadgarmage/proto3parser
Author: xiaochun.liu
Author-email: liuxiaochun@apache.org
License: UNKNOWN
Platform: UNKNOWN
Classifier: Programming Language :: Python :: 3
Classifier: License :: OSI Approved :: Apache Software License
Classifier: Operating System :: OS Independent
Classifier: Topic :: Software Development :: Libraries :: Python Modules
